{
  "b": "é_B___È",
  "blue": "é_Blue_________È",
  "deleteColor": "é_Delete color_____________È",
  "g": "é_G___È",
  "green": "é_Green___________È",
  "h": "é_H___È",
  "hsv": "é_HSV_______È",
  "hex": "é_Hex_______È",
  "hue": "é_Hue_______È",
  "noColor": "é_No color_________________È",
  "r": "é_R___È",
  "red": "é_Red_______È",
  "rgb": "é_RGB_______È",
  "s": "é_S___È",
  "saturation": "é_Saturation_____________________È",
  "saveColor": "é_Save color_____________________È",
  "saved": "é_Saved___________È",
  "v": "é_V___È",
  "value": "é_Value___________È"
}
