{
  "chooseTimeZone": "เลือกโซนเวลา",
  "timeZoneLabel": "({offset}) {cities}",
  "Africa/Bujumbura": "บูจุมบูรา กาโบโรน ลูบุมบาชิ ไคโร มาเซรู ทรีโพลี บลานไทร์",
  "Africa/Ceuta": "เซวตา",
  "Africa/Djibouti": "จิบูติ แอสมารา แอดดิสอาบาบา ไนโรบี โมกาดิชู ดาร์เอสซาลาม แคมพาลา",
  "Africa/El_Aaiun": "เอลเออุน คาซาบลังกา",
  "Africa/Luanda": "ลูอันดา พอร์โตโนโว คินชาซา แบงกุย บราสซาวิลล์ โดอาลา อัลเจียร์",
  "Africa/Ouagadougou": "อูกาโดวโกว อาบิดจาน แอคครา แบนจุล โคแนครี บิสซอ มอนโรเวีย",
  "America/Adak": "อาดัก",
  "America/Anchorage": "อันชอเรจ จูนิว ซิทคา เมทลาคัทลา ยาคูทัท โนม",
  "America/Antigua": "แอนติกัว แอนกวิลลา อารูบา บาร์เบดอส เซนต์บาร์เธเลมี ลาพาส คราเลนดิจ",
  "America/Argentina/Buenos_Aires": "บัวโนสไอเรส คอร์โดบา ซอลทา จูจาย ทูคูมาน คาทามาร์คา ลารีโอจา",
  "America/Asuncion": "อาซุนซิออง",
  "America/Belem": "เบเลม ฟอร์ทาเลซา เรซิฟี อารากัวอินา มาเซโอ บาเฮีย เซาเปาโล",
  "America/Belize": "เบลิซ เรจินา สวิฟต์เคอร์เรนท์ คอสตาริกา กัวเตมาลา เทกูซิกัลพา มานากัว",
  "America/Creston": "เครสตัน ดอว์สันครีก ฟอร์ทเนลสัน ไวท์ฮอร์ส ดอว์สัน เฮอร์โมซิลโล ฟินิกส์",
  "America/Danmarkshavn": "ดันมาร์คชาฟ",
  "America/Edmonton": "เอ็ดมอนตัน แคมบริดจ์เบย์ เยลโลว์ไนฟ์ อินูวิค โอจินากา เดนเวอร์ บอยส์",
  "America/Eirunepe": "เอรูเนพี รีโอบรังโก อาทิโคคัน โบโกตา กูอายาควิล จาไมกา เคย์แมน",
  "America/Halifax": "ฮาลิแฟกซ์ เกลซเบย์ มองค์ตัน กูซเบย์ ธูเล",
  "America/Mazatlan": "มาแซทลัน ชิฮัวฮัว",
  "America/Mexico_City": "เม็กซิโกซิตี้ เมริดา มอนเทอร์เรย์ บาเฮียบันเดรัส",
  "America/Miquelon": "มีเกอลง",
  "America/Nassau": "นาสซอ โทรอนโต นิพิกอน ธันเดอร์เบย์ อิคาลูอิท แพงนีร์ทุง ฮาวานา",
  "America/Noronha": "โนรอนฮา",
  "America/Nuuk": "นูอุค",
  "America/Santiago": "ซานทีอาโก",
  "America/Scoresbysund": "สคอเรสบีซุนด์",
  "America/St_Johns": "เซนต์ จอห์นส์",
  "America/Vancouver": "แวนคูเวอร์ ทิฮัวนา ลอสแองเจลิส",
  "America/Winnipeg": "วินนิเพ็ก เรนนีริเวอร์ เรโซลูท แรนคิทอินเล็ท มาทาโมรอส ชิคาโก มีโนมินี",
  "Antarctica/Casey": "เคซีย์",
  "Antarctica/Davis": "เดวิส",
  "Antarctica/DumontDUrville": "ดูมอนต์ ดีอูร์วิลล์",
  "Antarctica/Macquarie": "แมคควอรี",
  "Antarctica/Mawson": "มอว์สัน",
  "Antarctica/McMurdo": "แมคเมอร์โด",
  "Antarctica/Palmer": "ปาล์มเมอร์ โรเธรา",
  "Antarctica/Syowa": "ไซโอวา",
  "Antarctica/Troll": "ทรอล",
  "Antarctica/Vostok": "วอทตอค",
  "Arctic/Longyearbyen": "ลองเยียร์บายน์",
  "Asia/Amman": "อัมมาน",
  "Asia/Bahrain": "บาห์เรน แบกแดด คูเวต กาตาร์ ริยาดห์ เอเดน",
  "Asia/Beirut": "เบรุต",
  "Asia/Brunei": "บรูไน เซี่ยงไฮ้ ฮ่องกง มาคาสซาร์ อูลานบาตาร์ ชอยบัลแซน มาเก๊า",
  "Asia/Damascus": "ดามัสกัส",
  "Asia/Dhaka": "ดาการ์ ธิมภู อุรุมคี บิชเคค อัลมาที คอสทาเนย์ ออมสค์",
  "Asia/Dubai": "ดูไบ เยเรวาน บาคู ทบิลิซี มัสแคท",
  "Asia/Gaza": "กาซา เฮบรอน",
  "Asia/Jakarta": "จาการ์ตา พอนเทียแนค พนมเปญ เวียงจันทน์ ฮอฟด์ โนโวซิบิซ บาร์นาอุล",
  "Asia/Jayapura": "จายาปุระ โตเกียว เปียงยาง โซล ชิทา ยาคุตส์ คานดีกา",
  "Asia/Jerusalem": "เยรูซาเล็ม",
  "Asia/Kabul": "คาบุล",
  "Asia/Kamchatka": "คัมชัทคา อนาดีร์",
  "Asia/Kathmandu": "กาฐมาณฑุ",
  "Asia/Kolkata": "คอลคาทา โคลอมโบ",
  "Asia/Magadan": "มากาดัน ซาคฮาลิน ซเรดเนโคลิมสค์",
  "Asia/Nicosia": "นิโคเชีย ฟามากุสตา",
  "Asia/Qyzylorda": "คีซีลอร์ดา แอคโทบี แอคทอ อาทีรอ โอรัล คาราจี เยคาเทรินเบิร์ก",
  "Asia/Tehran": "เตห์ราน",
  "Asia/Vladivostok": "วลาดีวอสตอค อุสเนรา",
  "Asia/Yangon": "ย่างกุ้ง",
  "Atlantic/Azores": "อะซอเรส",
  "Atlantic/Bermuda": "เบอร์มิวดา",
  "Atlantic/Canary": "คานารี ฟาโร มาเดรา",
  "Atlantic/Cape_Verde": "เคปเวิร์ด",
  "Atlantic/Reykjavik": "เรย์คจาวิค เซนต์เฮเลนา",
  "Atlantic/South_Georgia": "เซาท์จอร์เจีย",
  "Atlantic/Stanley": "สแตนเลย์",
  "Australia/Brisbane": "บริสเบน ลินเดอแมน",
  "Australia/Broken_Hill": "โบรเคนฮิลล์ แอดิเลด",
  "Australia/Darwin": "ดาร์วิน",
  "Australia/Eucla": "ยุคลา",
  "Australia/Hobart": "โฮบาร์ท เมลเบิร์น ซิดนีย์",
  "Australia/Lord_Howe": "ลอร์ดฮาว",
  "Australia/Perth": "เพิร์ธ",
  "Europe/Andorra": "แอนดอร์รา ทิเรน เวียนนา ซาราเจโว บรัสเซลส์ ซูริช ปราก",
  "Europe/Astrakhan": "แอสทราคาน ซาราทอฟ อุลยานอฟสค์ ซามารา",
  "Europe/Kaliningrad": "คาลินินกราด",
  "Europe/London": "ลอนดอน เกิร์นซีย์ ดับลิน ไอเซิลออฟแมน เจอร์ซีน ลิสบอน",
  "Europe/Mariehamn": "มารีแฮม โซเฟีย ทัลลินน์ เฮลซิงกิ เอเธนส์ วิลเนียส ริกา",
  "Europe/Minsk": "มินสค์ มอสโค ซิมเฟโรพอล คีรอฟ วอลโกกราด อิสตันบูล",
  "Indian/Chagos": "ชากอส",
  "Indian/Christmas": "คริสต์มาส",
  "Indian/Cocos": "โกกอส",
  "Indian/Comoro": "โคโมโร แอนทานานารีโว มายอตต์",
  "Indian/Maldives": "มัลดีฟส์ เคอร์กุเลน",
  "Indian/Mauritius": "มอริเชียส เรอูนิยง มาเฮ",
  "Pacific/Apia": "อาเพีย",
  "Pacific/Auckland": "อัคแลนด์",
  "Pacific/Chatham": "ชัทแฮม",
  "Pacific/Chuuk": "ชูอุค กวม ไซพาน พอร์ตโมเรสบี",
  "Pacific/Easter": "อีสเตอร์",
  "Pacific/Enderbury": "เอนเดอร์บิวรี ฟาคาโอโฟ ทองกาทาปู",
  "Pacific/Fiji": "ฟิจิ",
  "Pacific/Galapagos": "กาลาปากอส",
  "Pacific/Gambier": "แกมเบียร์",
  "Pacific/Kiritimati": "คิรีทีมาที",
  "Pacific/Marquesas": "มาร์เคซาส",
  "Pacific/Norfolk": "นอร์ฟอล์ก",
  "Pacific/Pago_Pago": "ปาโกปาโก นีอูเอ มิดเวย์",
  "Pacific/Palau": "ปาเลา",
  "Pacific/Pitcairn": "หมู่เกาะพิตแคร์น อังกฤษ",
  "Pacific/Pohnpei": "ปอห์นเป คอสแร นูวมีเอ บูเกนวิลล์ กัวดัลคานาล เอฟาเต",
  "Pacific/Rarotonga": "ราโรทองกา ตาฮิติ โฮโนลูลู",
  "Pacific/Tarawa": "ทาราวา มาจูโร ควาเจเลอิน นาอูรู ฟูนาฟูตี วาเกะ วัลลิส"
}
