{
  "chooseTimeZone": "Wybierz strefę czasową",
  "timeZoneLabel": "({offset}) {cities}",
  "Africa/Bujumbura": "Bużumbura, Gaborone, Lubumbashi, Kair, Maseru, Trypolis, Blantyre",
  "Africa/Ceuta": "Ceuta",
  "Africa/Djibouti": "Dżibuti, Asmara, Addis Ababa, Nairobi, Mogadiszu, Dar es Salaam, Kampala",
  "Africa/El_Aaiun": "El Aaiun, Casablanca",
  "Africa/Luanda": "Luanda, Porto-Novo, Kinszasa, Bangui, Brazzaville, Duala, Algier",
  "Africa/Ouagadougou": "Wagadugu, Abidżan, Accra, Bandżul, Konakry, Bissau, Monrovia",
  "America/Adak": "Adak",
  "America/Anchorage": "Anchorage, Juneau, Sitka, Metlakatla, Yakutat, Nome",
  "America/Antigua": "Antigua, Anguilla, Aruba, Barbados, St Barthelemy, La Paz, Kralendijk",
  "America/Argentina/Buenos_Aires": "Buenos Aires, Cordoba, Salta, Jujuy, Tucuman, Catamarca, La Rioja",
  "America/Asuncion": "Asuncion",
  "America/Belem": "Belem, Fortaleza, Recife, Araguaina, Maceio, Bahia, Sao Paulo",
  "America/Belize": "Belize, Regina, Swift Current, Kostaryka, Gwatemala, Tegucigalpa, Managua",
  "America/Creston": "Creston, Dawson Creek, Fort Nelson, Whitehorse, Dawson, Hermosillo, Phoenix",
  "America/Danmarkshavn": "Danmarkshavn",
  "America/Edmonton": "Edmonton, Cambridge Bay, Yellowknife, Inuvik, Ojinaga, Denver, Boise",
  "America/Eirunepe": "Eirunepe, Rio Branco, Atikokan, Bogota, Guayaquil, Jamajka, Kajmany",
  "America/Halifax": "Halifax, Glace Bay, Moncton, Goose Bay, Thule",
  "America/Mazatlan": "Mazatlan, Chihuahua",
  "America/Mexico_City": "Meksyk, Merida, Monterrey, Bahia Banderas",
  "America/Miquelon": "Miquelon",
  "America/Nassau": "Nassau, Toronto, Nipigon, Thunder Bay, Iqaluit, Pangnirtung, Hawana",
  "America/Noronha": "Noronha",
  "America/Nuuk": "Nuuk",
  "America/Santiago": "Santiago",
  "America/Scoresbysund": "Scoresbysund",
  "America/St_Johns": "Rzeka Świętego Jana",
  "America/Vancouver": "Vancouver, Tijuana, Los Angeles",
  "America/Winnipeg": "Winnipeg, Rainy River, Resolute, Rankin Inlet, Matamoros, Chicago, Menominee",
  "Antarctica/Casey": "Casey",
  "Antarctica/Davis": "Davis",
  "Antarctica/DumontDUrville": "Dumont d'Urville",
  "Antarctica/Macquarie": "Macquarie",
  "Antarctica/Mawson": "Mawson",
  "Antarctica/McMurdo": "McMurdo",
  "Antarctica/Palmer": "Palmer, Rothera",
  "Antarctica/Syowa": "Syowa",
  "Antarctica/Troll": "Troll",
  "Antarctica/Vostok": "Wostok",
  "Arctic/Longyearbyen": "Longyearbyen",
  "Asia/Amman": "Amman",
  "Asia/Bahrain": "Bahrajn, Bagdad, Kuweit, Katar, Rijad, Aden",
  "Asia/Beirut": "Bejrut",
  "Asia/Brunei": "Brunei, Szanghaj, Hong Kong, Makasar, Ułan Bator, Choibalsan, Makau",
  "Asia/Damascus": "Damaszek",
  "Asia/Dhaka": "Dakka, Thimphu, Urumqi, Biszkek, Ałmaty, Kustanaj, Omsk",
  "Asia/Dubai": "Dubaj, Erywań, Baku, Tbilisi, Muscat",
  "Asia/Gaza": "Gaza, Hebron",
  "Asia/Jakarta": "Dżakarta, Pontianak, Phnom Penh, Wientian, Kobdo, Nowosybirsk, Barnauł",
  "Asia/Jayapura": "Jayapura, Tokio, Pjongjang, Seul, Chita, Jakuck, Chandyga",
  "Asia/Jerusalem": "Jerozolima",
  "Asia/Kabul": "Kabul",
  "Asia/Kamchatka": "Kamczatka, Anadyr",
  "Asia/Kathmandu": "Katmandu",
  "Asia/Kolkata": "Kalkuta, Kolombo",
  "Asia/Magadan": "Magadan, Sachalin, Sriedniekołymsk",
  "Asia/Nicosia": "Nikozja, Famagusta",
  "Asia/Qyzylorda": "Kyzyłorda, Aktobe, Aktau, Atyrau, Orał, Karaczi, Jekaterynburg",
  "Asia/Tehran": "Teheran",
  "Asia/Vladivostok": "Władywostok, Ust´-Niera",
  "Asia/Yangon": "Rangun",
  "Atlantic/Azores": "Azory",
  "Atlantic/Bermuda": "Bermudy",
  "Atlantic/Canary": "Kanary, Faroe, Madera",
  "Atlantic/Cape_Verde": "Republika Zielonego Przylądka",
  "Atlantic/Reykjavik": "Reykjavík, Święta Helena",
  "Atlantic/South_Georgia": "Georgia Południowa",
  "Atlantic/Stanley": "Stanley",
  "Australia/Brisbane": "Brisbane, Lindeman",
  "Australia/Broken_Hill": "Broken Hill, Adelaide",
  "Australia/Darwin": "Darwin",
  "Australia/Eucla": "Eucla",
  "Australia/Hobart": "Hobart, Melbourne, Sydney",
  "Australia/Lord_Howe": "Lord Howe",
  "Australia/Perth": "Perth",
  "Europe/Andorra": "Andora, Tirana, Wiedeń, Sarajewo, Bruksela, Zurych, Praga",
  "Europe/Astrakhan": "Astrachań, Saratow, Uljanowsk, Samara",
  "Europe/Kaliningrad": "Królewiec",
  "Europe/London": "Londyn, Guernsey, Dublin, Wyspa Man, Jersey, Lizbona",
  "Europe/Mariehamn": "Mariehamn, Sofia, Tallinn, Helsinki, Ateny, Wilno, Ryga",
  "Europe/Minsk": "Mińsk, Moskwa, Symferopol, Kirow, Wołgograd, Stambuł",
  "Indian/Chagos": "Czagos",
  "Indian/Christmas": "Wyspa Bożego Narodzenia",
  "Indian/Cocos": "Wyspy Kokosowe",
  "Indian/Comoro": "Komory, Antananarywa, Majotta",
  "Indian/Maldives": "Malediwy, Wyspy Kerguelena",
  "Indian/Mauritius": "Mauritius, Reunion, Mahe",
  "Pacific/Apia": "Apia",
  "Pacific/Auckland": "Auckland",
  "Pacific/Chatham": "Chatham",
  "Pacific/Chuuk": "Chuuk, Guam, Saipan, Port Moresby",
  "Pacific/Easter": "Wyspa Wielkanocna",
  "Pacific/Enderbury": "Enderbury, Fakaofo, Tongatapu",
  "Pacific/Fiji": "Fidżi",
  "Pacific/Galapagos": "Galapagos",
  "Pacific/Gambier": "Wyspy Gambiera",
  "Pacific/Kiritimati": "Kiritimati",
  "Pacific/Marquesas": "Markizy",
  "Pacific/Norfolk": "Norfolk",
  "Pacific/Pago_Pago": "Pago Pago, Niue, Midway",
  "Pacific/Palau": "Palau",
  "Pacific/Pitcairn": "Pitcairn",
  "Pacific/Pohnpei": "Pohnpei, Kosrae, Noumea, Bougainville, Guadalcanal, Efate",
  "Pacific/Rarotonga": "Rarotonga, Tahiti, Honolulu",
  "Pacific/Tarawa": "Tarawa, Majuro, Kwajalein, Nauru, Funafuti, Wake, Wallis"
}
