{
  "color": {
    "background": {
      "default": {
        "value": "{core.color.neutral.blk-190}",
        "type": "color"
      }
    },
    "foreground": {
      "1": {
        "value": "{core.color.neutral.blk-200}",
        "type": "color"
      },
      "2": {
        "value": "{core.color.neutral.blk-210}",
        "type": "color"
      },
      "3": {
        "value": "{core.color.neutral.blk-220}",
        "type": "color"
      },
      "current": {
        "value": "#214155",
        "type": "color",
        "description": "medium-saturation core tokens missing. Should be: core.color.medium-saturation.m-bb-090"
      },
      "scrim": {
        "value": "{core.color.neutral.blk-240}",
        "type": "color"
      }
    },
    "transparent": {
      "default": {
        "value": "{core.color.neutral.blk-000}",
        "type": "color",
        "$extensions": {
          "studio.tokens": {
            "modify": {
              "type": "alpha",
              "value": "0",
              "space": "lch"
            }
          }
        }
      },
      "hover": {
        "value": "{core.color.neutral.blk-000}",
        "type": "color",
        "$extensions": {
          "studio.tokens": {
            "modify": {
              "type": "alpha",
              "value": ".04",
              "space": "lch"
            }
          }
        }
      },
      "press": {
        "value": "{core.color.neutral.blk-000}",
        "type": "color",
        "$extensions": {
          "studio.tokens": {
            "modify": {
              "type": "alpha",
              "value": ".08",
              "space": "lch"
            }
          }
        }
      },
      "scrim": {
        "value": "{core.color.neutral.blk-240}",
        "type": "color",
        "$extensions": {
          "studio.tokens": {
            "modify": {
              "type": "alpha",
              "value": ".85",
              "space": "lch"
            }
          }
        }
      }
    },
    "brand": {
      "default": {
        "value": "{core.color.vibrant.blue.v-bb-160}",
        "type": "color"
      },
      "hover": {
        "value": "{core.color.high-saturation.blue.h-bb-060}",
        "type": "color"
      },
      "press": {
        "value": "{core.color.high-saturation.blue.h-bb-070}",
        "type": "color"
      }
    },
    "status": {
      "info": {
        "default": {
          "value": "{core.color.dark.blue.d-bb-420}",
          "type": "color"
        },
        "hover": {
          "value": "{core.color.vibrant.blue.v-bb-140}",
          "type": "color"
        },
        "press": {
          "value": "{core.color.vibrant.blue.v-bb-160}",
          "type": "color"
        }
      },
      "success": {
        "default": {
          "value": "{core.color.dark.green.d-gg-420}",
          "type": "color"
        },
        "hover": {
          "value": "{core.color.vibrant.green.v-gg-140}",
          "type": "color"
        },
        "press": {
          "value": "{core.color.vibrant.green.v-gg-160}",
          "type": "color"
        }
      },
      "warning": {
        "default": {
          "value": "{core.color.dark.yellow.d-yy-420}",
          "type": "color"
        },
        "hover": {
          "value": "{core.color.vibrant.yellow.v-yy-140}",
          "type": "color"
        },
        "press": {
          "value": "{core.color.vibrant.yellow.v-yy-160}",
          "type": "color"
        }
      },
      "danger": {
        "default": {
          "value": "{core.color.dark.red.d-rr-420}",
          "type": "color"
        },
        "hover": {
          "value": "{core.color.vibrant.red.v-rr-140}",
          "type": "color"
        },
        "press": {
          "value": "{core.color.vibrant.red.v-rr-160}",
          "type": "color"
        }
      }
    },
    "inverse": {
      "default": {
        "value": "{core.color.neutral.blk-005}",
        "type": "color"
      },
      "hover": {
        "value": "{core.color.neutral.blk-000}",
        "type": "color"
      },
      "press": {
        "value": "{core.color.neutral.blk-010}",
        "type": "color"
      }
    },
    "text": {
      "1": {
        "value": "{core.color.neutral.blk-000}",
        "type": "color"
      },
      "2": {
        "value": "{core.color.neutral.blk-060}",
        "type": "color"
      },
      "3": {
        "value": "{core.color.neutral.blk-090}",
        "type": "color"
      },
      "inverse": {
        "value": "{core.color.neutral.blk-220}",
        "type": "color"
      },
      "link": {
        "value": "{core.color.dark.blue.d-bb-420}",
        "type": "color"
      }
    },
    "border": {
      "1": {
        "value": "{core.color.neutral.blk-160}",
        "type": "color"
      },
      "2": {
        "value": "{core.color.neutral.blk-170}",
        "type": "color"
      },
      "3": {
        "value": "{core.color.neutral.blk-180}",
        "type": "color"
      },
      "input": {
        "value": "{core.color.neutral.blk-130}",
        "type": "color"
      }
    }
  }
}
